<annotation>
	<folder>ImageSets</folder>
<filename>23.23.jpg</filename>	<path>/Users/sarthak/Projects/enics/Corrected_annotations_ImageSets/ImageSets/23.23.jpg</path>
	<source>
		<database>Unknown</database>
	</source>
	<size>
		<width>3840</width>
		<height>2748</height>
		<depth>3</depth>
	</size>
	<segmented>0</segmented>
	<object>
		<name>1_a</name>
		<pose>Unspecified</pose>
		<truncated>0</truncated>
		<rotated>0</rotated>
		<bndbox>
			<xmin>777</xmin>
			<ymin>379</ymin>
			<xmax>1365</xmax>
			<ymax>562</ymax>
		</bndbox>
	</object>
	<object>
		<name>2_a</name>
		<pose>Unspecified</pose>
		<truncated>0</truncated>
		<rotated>0</rotated>
		<bndbox>
			<xmin>1388</xmin>
			<ymin>380</ymin>
			<xmax>1977</xmax>
			<ymax>540</ymax>
		</bndbox>
	</object>
	<object>
		<name>3_b</name>
		<pose>Unspecified</pose>
		<truncated>0</truncated>
		<rotated>0</rotated>
		<bndbox>
			<xmin>2090</xmin>
			<ymin>508</ymin>
			<xmax>2147</xmax>
			<ymax>675</ymax>
		</bndbox>
	</object>
	<object>
		<name>4_b</name>
		<pose>Unspecified</pose>
		<truncated>0</truncated>
		<rotated>0</rotated>
		<bndbox>
			<xmin>2166</xmin>
			<ymin>507</ymin>
			<xmax>2215</xmax>
			<ymax>680</ymax>
		</bndbox>
	</object>
	<object>
		<name>5_c</name>
		<pose>Unspecified</pose>
		<truncated>0</truncated>
		<rotated>0</rotated>
		<bndbox>
			<xmin>2251</xmin>
			<ymin>484</ymin>
			<xmax>2369</xmax>
			<ymax>723</ymax>
		</bndbox>
	</object>
	<object>
		<name>6_6</name>
		<pose>Unspecified</pose>
		<truncated>0</truncated>
		<rotated>0</rotated>
		<bndbox>
			<xmin>2378</xmin>
			<ymin>393</ymin>
			<xmax>2660</xmax>
			<ymax>763</ymax>
		</bndbox>
	</object>
	<object>
		<name>7_c</name>
		<pose>Unspecified</pose>
		<truncated>0</truncated>
		<rotated>0</rotated>
		<bndbox>
			<xmin>2678</xmin>
			<ymin>369</ymin>
			<xmax>2790</xmax>
			<ymax>628</ymax>
		</bndbox>
	</object>
	<object>
		<name>8_d</name>
		<pose>Unspecified</pose>
		<truncated>0</truncated>
		<rotated>0</rotated>
		<bndbox>
			<xmin>2865</xmin>
			<ymin>380</ymin>
			<xmax>3038</xmax>
			<ymax>427</ymax>
		</bndbox>
	</object>
	<object>
		<name>9_d</name>
		<pose>Unspecified</pose>
		<truncated>0</truncated>
		<rotated>0</rotated>
		<bndbox>
			<xmin>2863</xmin>
			<ymin>440</ymin>
			<xmax>3032</xmax>
			<ymax>498</ymax>
		</bndbox>
	</object>
	<object>
		<name>10_p</name>
		<pose>Unspecified</pose>
		<truncated>0</truncated>
		<rotated>0</rotated>
		<bndbox>
			<xmin>2787</xmin>
			<ymin>587</ymin>
			<xmax>2999</xmax>
			<ymax>666</ymax>
		</bndbox>
	</object>
	<object>
		<name>11_q</name>
		<pose>Unspecified</pose>
		<truncated>0</truncated>
		<rotated>0</rotated>
		<bndbox>
			<xmin>3015</xmin>
			<ymin>500</ymin>
			<xmax>3181</xmax>
			<ymax>815</ymax>
		</bndbox>
	</object>
	<object>
		<name>12_r</name>
		<pose>Unspecified</pose>
		<truncated>0</truncated>
		<rotated>0</rotated>
		<bndbox>
			<xmin>2693</xmin>
			<ymin>654</ymin>
			<xmax>3005</xmax>
			<ymax>769</ymax>
		</bndbox>
	</object>
	<object>
		<name>13_s</name>
		<pose>Unspecified</pose>
		<truncated>0</truncated>
		<rotated>0</rotated>
		<bndbox>
			<xmin>643</xmin>
			<ymin>572</ymin>
			<xmax>749</xmax>
			<ymax>782</ymax>
		</bndbox>
	</object>
	<object>
		<name>14_t</name>
		<pose>Unspecified</pose>
		<truncated>0</truncated>
		<rotated>0</rotated>
		<bndbox>
			<xmin>896</xmin>
			<ymin>643</ymin>
			<xmax>1063</xmax>
			<ymax>841</ymax>
		</bndbox>
	</object>
	<object>
		<name>15_e</name>
		<pose>Unspecified</pose>
		<truncated>0</truncated>
		<rotated>0</rotated>
		<bndbox>
			<xmin>1453</xmin>
			<ymin>777</ymin>
			<xmax>1519</xmax>
			<ymax>905</ymax>
		</bndbox>
	</object>
	<object>
		<name>16_k</name>
		<pose>Unspecified</pose>
		<truncated>0</truncated>
		<rotated>0</rotated>
		<bndbox>
			<xmin>1569</xmin>
			<ymin>784</ymin>
			<xmax>1685</xmax>
			<ymax>902</ymax>
		</bndbox>
	</object>
	<object>
		<name>17_u</name>
		<pose>Unspecified</pose>
		<truncated>0</truncated>
		<rotated>0</rotated>
		<bndbox>
			<xmin>1917</xmin>
			<ymin>625</ymin>
			<xmax>2038</xmax>
			<ymax>1009</ymax>
		</bndbox>
	</object>
	<object>
		<name>18_v</name>
		<pose>Unspecified</pose>
		<truncated>0</truncated>
		<rotated>0</rotated>
		<bndbox>
			<xmin>2088</xmin>
			<ymin>965</ymin>
			<xmax>2219</xmax>
			<ymax>1030</ymax>
		</bndbox>
	</object>
	<object>
		<name>19_w</name>
		<pose>Unspecified</pose>
		<truncated>0</truncated>
		<rotated>0</rotated>
		<bndbox>
			<xmin>2256</xmin>
			<ymin>1076</ymin>
			<xmax>2482</xmax>
			<ymax>1170</ymax>
		</bndbox>
	</object>
	<object>
		<name>20_f</name>
		<pose>Unspecified</pose>
		<truncated>0</truncated>
		<rotated>0</rotated>
		<bndbox>
			<xmin>2366</xmin>
			<ymin>882</ymin>
			<xmax>2474</xmax>
			<ymax>1002</ymax>
		</bndbox>
	</object>
	<object>
		<name>21_g</name>
		<pose>Unspecified</pose>
		<truncated>0</truncated>
		<rotated>0</rotated>
		<bndbox>
			<xmin>2535</xmin>
			<ymin>725</ymin>
			<xmax>2900</xmax>
			<ymax>1079</ymax>
		</bndbox>
	</object>
	<object>
		<name>22_g</name>
		<pose>Unspecified</pose>
		<truncated>0</truncated>
		<rotated>0</rotated>
		<bndbox>
			<xmin>2897</xmin>
			<ymin>836</ymin>
			<xmax>3256</xmax>
			<ymax>1186</ymax>
		</bndbox>
	</object>
	<object>
		<name>23_h</name>
		<pose>Unspecified</pose>
		<truncated>0</truncated>
		<rotated>0</rotated>
		<bndbox>
			<xmin>628</xmin>
			<ymin>1020</ymin>
			<xmax>819</xmax>
			<ymax>1381</ymax>
		</bndbox>
	</object>
	<object>
		<name>24_h</name>
		<pose>Unspecified</pose>
		<truncated>0</truncated>
		<rotated>0</rotated>
		<bndbox>
			<xmin>624</xmin>
			<ymin>1416</ymin>
			<xmax>817</xmax>
			<ymax>1773</ymax>
		</bndbox>
	</object>
	<object>
		<name>25_f</name>
		<pose>Unspecified</pose>
		<truncated>0</truncated>
		<rotated>0</rotated>
		<bndbox>
			<xmin>876</xmin>
			<ymin>2299</ymin>
			<xmax>992</xmax>
			<ymax>2384</ymax>
		</bndbox>
	</object>
	<object>
		<name>26_f</name>
		<pose>Unspecified</pose>
		<truncated>0</truncated>
		<rotated>0</rotated>
		<bndbox>
			<xmin>1449</xmin>
			<ymin>2240</ymin>
			<xmax>1560</xmax>
			<ymax>2370</ymax>
		</bndbox>
	</object>
	<object>
		<name>27_x</name>
		<pose>Unspecified</pose>
		<truncated>0</truncated>
		<rotated>1</rotated>
		<bndbox>
			<xmin>1569</xmin>
			<ymin>2261</ymin>
			<xmax>2005</xmax>
			<ymax>2379</ymax>
		</bndbox>
	</object>
	<object>
		<name>28_i</name>
		<pose>Unspecified</pose>
		<truncated>0</truncated>
		<rotated>0</rotated>
		<bndbox>
			<xmin>1914</xmin>
			<ymin>1948</ymin>
			<xmax>2097</xmax>
			<ymax>2125</ymax>
		</bndbox>
	</object>
	<object>
		<name>29_i</name>
		<pose>Unspecified</pose>
		<truncated>0</truncated>
		<rotated>0</rotated>
		<bndbox>
			<xmin>1737</xmin>
			<ymin>1951</ymin>
			<xmax>1919</xmax>
			<ymax>2157</ymax>
		</bndbox>
	</object>
	<object>
		<name>30_i</name>
		<pose>Unspecified</pose>
		<truncated>0</truncated>
		<rotated>1</rotated>
		<bndbox>
			<xmin>1590</xmin>
			<ymin>2057</ymin>
			<xmax>1784</xmax>
			<ymax>2266</ymax>
		</bndbox>
	</object>
	<object>
		<name>31_j</name>
		<pose>Unspecified</pose>
		<truncated>0</truncated>
		<rotated>0</rotated>
		<bndbox>
			<xmin>1775</xmin>
			<ymin>2143</ymin>
			<xmax>1896</xmax>
			<ymax>2266</ymax>
		</bndbox>
	</object>
	<object>
		<name>32_j</name>
		<pose>Unspecified</pose>
		<truncated>0</truncated>
		<rotated>0</rotated>
		<bndbox>
			<xmin>1887</xmin>
			<ymin>2093</ymin>
			<xmax>2025</xmax>
			<ymax>2248</ymax>
		</bndbox>
	</object>
	<object>
		<name>33_e</name>
		<pose>Unspecified</pose>
		<truncated>0</truncated>
		<rotated>0</rotated>
		<bndbox>
			<xmin>1381</xmin>
			<ymin>1169</ymin>
			<xmax>1444</xmax>
			<ymax>1302</ymax>
		</bndbox>
	</object>
	<object>
		<name>34_k</name>
		<pose>Unspecified</pose>
		<truncated>0</truncated>
		<rotated>0</rotated>
		<bndbox>
			<xmin>2340</xmin>
			<ymin>2016</ymin>
			<xmax>2462</xmax>
			<ymax>2150</ymax>
		</bndbox>
	</object>
	<object>
		<name>35_k</name>
		<pose>Unspecified</pose>
		<truncated>0</truncated>
		<rotated>0</rotated>
		<bndbox>
			<xmin>2490</xmin>
			<ymin>2015</ymin>
			<xmax>2607</xmax>
			<ymax>2127</ymax>
		</bndbox>
	</object>
	<object>
		<name>36_i</name>
		<pose>Unspecified</pose>
		<truncated>0</truncated>
		<rotated>0</rotated>
		<bndbox>
			<xmin>2656</xmin>
			<ymin>1991</ymin>
			<xmax>2828</xmax>
			<ymax>2166</ymax>
		</bndbox>
	</object>
	<object>
		<name>37_i</name>
		<pose>Unspecified</pose>
		<truncated>0</truncated>
		<rotated>0</rotated>
		<bndbox>
			<xmin>2858</xmin>
			<ymin>1989</ymin>
			<xmax>3031</xmax>
			<ymax>2170</ymax>
		</bndbox>
	</object>
	<object>
		<name>38_l</name>
		<pose>Unspecified</pose>
		<truncated>0</truncated>
		<rotated>0</rotated>
		<bndbox>
			<xmin>2258</xmin>
			<ymin>2231</ymin>
			<xmax>2637</xmax>
			<ymax>2352</ymax>
		</bndbox>
	</object>
	<object>
		<name>39_l</name>
		<pose>Unspecified</pose>
		<truncated>0</truncated>
		<rotated>0</rotated>
		<bndbox>
			<xmin>2713</xmin>
			<ymin>2339</ymin>
			<xmax>3065</xmax>
			<ymax>2460</ymax>
		</bndbox>
	</object>
	<object>
		<name>40_l</name>
		<pose>Unspecified</pose>
		<truncated>0</truncated>
		<rotated>0</rotated>
		<bndbox>
			<xmin>2602</xmin>
			<ymin>1670</ymin>
			<xmax>2997</xmax>
			<ymax>1807</ymax>
		</bndbox>
	</object>
	<object>
		<name>41_y</name>
		<pose>Unspecified</pose>
		<truncated>0</truncated>
		<rotated>0</rotated>
		<bndbox>
			<xmin>2406</xmin>
			<ymin>1188</ymin>
			<xmax>2530</xmax>
			<ymax>1548</ymax>
		</bndbox>
	</object>
	<object>
		<name>42_z</name>
		<pose>Unspecified</pose>
		<truncated>0</truncated>
		<rotated>0</rotated>
		<bndbox>
			<xmin>3085</xmin>
			<ymin>1741</ymin>
			<xmax>3178</xmax>
			<ymax>1887</ymax>
		</bndbox>
	</object>
	<object>
		<name>43_m</name>
		<pose>Unspecified</pose>
		<truncated>0</truncated>
		<rotated>0</rotated>
		<bndbox>
			<xmin>3031</xmin>
			<ymin>1895</ymin>
			<xmax>3172</xmax>
			<ymax>2057</ymax>
		</bndbox>
	</object>
	<object>
		<name>44_m</name>
		<pose>Unspecified</pose>
		<truncated>0</truncated>
		<rotated>0</rotated>
		<bndbox>
			<xmin>3025</xmin>
			<ymin>2072</ymin>
			<xmax>3175</xmax>
			<ymax>2219</ymax>
		</bndbox>
	</object>
	<object>
		<name>45_i</name>
		<pose>Unspecified</pose>
		<truncated>0</truncated>
		<rotated>0</rotated>
		<bndbox>
			<xmin>1147</xmin>
			<ymin>1815</ymin>
			<xmax>1260</xmax>
			<ymax>1930</ymax>
		</bndbox>
	</object>
	<object>
		<name>47_n</name>
		<pose>Unspecified</pose>
		<truncated>0</truncated>
		<rotated>0</rotated>
		<bndbox>
			<xmin>1397</xmin>
			<ymin>1938</ymin>
			<xmax>1488</xmax>
			<ymax>2007</ymax>
		</bndbox>
	</object>
	<object>
		<name>48_n</name>
		<pose>Unspecified</pose>
		<truncated>0</truncated>
		<rotated>0</rotated>
		<bndbox>
			<xmin>1407</xmin>
			<ymin>2061</ymin>
			<xmax>1508</xmax>
			<ymax>2130</ymax>
		</bndbox>
	</object>
	<object>
		<name>49_aa</name>
		<pose>Unspecified</pose>
		<truncated>0</truncated>
		<rotated>0</rotated>
		<bndbox>
			<xmin>1293</xmin>
			<ymin>1710</ymin>
			<xmax>1367</xmax>
			<ymax>1773</ymax>
		</bndbox>
	</object>
	<object>
		<name>46_n</name>
		<pose>Unspecified</pose>
		<truncated>0</truncated>
		<rotated>0</rotated>
		<bndbox>
			<xmin>2263</xmin>
			<ymin>1663</ymin>
			<xmax>2356</xmax>
			<ymax>1741</ymax>
		</bndbox>
	</object>
	<object>
		<name>50_n</name>
		<pose>Unspecified</pose>
		<truncated>0</truncated>
		<rotated>0</rotated>
		<bndbox>
			<xmin>2234</xmin>
			<ymin>1743</ymin>
			<xmax>2329</xmax>
			<ymax>1814</ymax>
		</bndbox>
	</object>
	<object>
		<name>51_n</name>
		<pose>Unspecified</pose>
		<truncated>0</truncated>
		<rotated>0</rotated>
		<bndbox>
			<xmin>2238</xmin>
			<ymin>1810</ymin>
			<xmax>2333</xmax>
			<ymax>1886</ymax>
		</bndbox>
	</object>
	<object>
		<name>52_ab</name>
		<pose>Unspecified</pose>
		<truncated>0</truncated>
		<rotated>0</rotated>
		<bndbox>
			<xmin>2249</xmin>
			<ymin>1269</ymin>
			<xmax>2315</xmax>
			<ymax>1364</ymax>
		</bndbox>
	</object>
	<object>
		<name>53_ac</name>
		<pose>Unspecified</pose>
		<truncated>0</truncated>
		<rotated>0</rotated>
		<bndbox>
			<xmin>2802</xmin>
			<ymin>1913</ymin>
			<xmax>3028</xmax>
			<ymax>1972</ymax>
		</bndbox>
	</object>
	<object>
		<name>54_ad</name>
		<pose>Unspecified</pose>
		<truncated>0</truncated>
		<rotated>0</rotated>
		<bndbox>
			<xmin>2021</xmin>
			<ymin>2119</ymin>
			<xmax>2068</xmax>
			<ymax>2307</ymax>
		</bndbox>
	</object>
	<object>
		<name>55_l</name>
		<pose>Unspecified</pose>
		<truncated>0</truncated>
		<rotated>0</rotated>
		<bndbox>
			<xmin>1624</xmin>
			<ymin>1735</ymin>
			<xmax>1989</xmax>
			<ymax>1864</ymax>
		</bndbox>
	</object>
	<object>
		<name>56_ae</name>
		<pose>Unspecified</pose>
		<truncated>0</truncated>
		<rotated>0</rotated>
		<bndbox>
			<xmin>1987</xmin>
			<ymin>1741</ymin>
			<xmax>2154</xmax>
			<ymax>1875</ymax>
		</bndbox>
	</object>
	<object>
		<name>57_af</name>
		<pose>Unspecified</pose>
		<truncated>0</truncated>
		<rotated>0</rotated>
		<bndbox>
			<xmin>2552</xmin>
			<ymin>1095</ymin>
			<xmax>2766</xmax>
			<ymax>1610</ymax>
		</bndbox>
	</object>
	<object>
		<name>58_i</name>
		<pose>Unspecified</pose>
		<truncated>0</truncated>
		<rotated>0</rotated>
		<bndbox>
			<xmin>2766</xmin>
			<ymin>1497</ymin>
			<xmax>2876</xmax>
			<ymax>1616</ymax>
		</bndbox>
	</object>
	<object>
		<name>59_o</name>
		<pose>Unspecified</pose>
		<truncated>0</truncated>
		<rotated>0</rotated>
		<bndbox>
			<xmin>1682</xmin>
			<ymin>609</ymin>
			<xmax>1776</xmax>
			<ymax>693</ymax>
		</bndbox>
	</object>
	<object>
		<name>60_o</name>
		<pose>Unspecified</pose>
		<truncated>0</truncated>
		<rotated>0</rotated>
		<bndbox>
			<xmin>1440</xmin>
			<ymin>609</ymin>
			<xmax>1542</xmax>
			<ymax>698</ymax>
		</bndbox>
	</object>
</annotation>
